skailar
