Metadata-Version: 2.1
Name: Skailar-framework
Version: 5.0
Summary: A Web framework made in Python
Home-page: https://www.skailarproject.com/
Author: Skailar-framework
Author-email: foundation@skailarproject.com
License: BSD-3-Clause
Project-URL: Documentation, https://docs.skailarproject.com/
Project-URL: Release notes, https://docs.skailarproject.com/en/stable/releases/
Project-URL: Funding, https://www.skailarproject.com/fundraising/
Project-URL: Source, https://github.com/skailar/skailar
Project-URL: Tracker, https://code.skailarproject.com/
Classifier: Programming Language :: Python :: 3
Classifier: License :: OSI Approved :: BSD License
Classifier: Operating System :: OS Independent
Requires-Python: >=3.10
Provides-Extra: argon2
Provides-Extra: bcrypt
License-File: LICENSE
License-File: LICENSE.python
License-File: AUTHORS
